<?xml version="1.0" encoding="UTF-8"?>
<language languagecode="de"
	xmlns="https://www.woltlab.com"
	xmlns:xsi="https://www.w3.org/2001/XMLSchema-instance"
	xsi:schemaLocation="https://www.woltlab.com https://www.woltlab.com/XSD/6.0/language.xsd">
	<import>
		<category name="wcf.acp.form">
			<item name="wcf.acp.form.minecraftAdd.dbHost"><![CDATA[Dynmap Datenbank Host]]></item>
			<item name="wcf.acp.form.minecraftAdd.dbHost.error"><![CDATA[Konnte nicht mit dem MySQL-Server verbinden.<br>(Meldung: {$msg})]]></item>
			<item name="wcf.acp.form.minecraftAdd.dbPort"><![CDATA[Dynmap Datenbank Port]]></item>
			<item name="wcf.acp.form.minecraftAdd.dbUser"><![CDATA[Dynmap Datenbank Benutzer]]></item>
			<item name="wcf.acp.form.minecraftAdd.dbPassword"><![CDATA[Dynmap Datenbank Passwort]]></item>
			<item name="wcf.acp.form.minecraftAdd.dbName"><![CDATA[Dynmap Datenbank Name]]></item>
			<item name="wcf.acp.form.minecraftAdd.webchatEnabled"><![CDATA[Webchat aktivieren]]></item>
			<item name="wcf.acp.form.minecraftAdd.webchatEnabled.description"><![CDATA[<kbd>allowwebchat</kbd> in der configuration.txt muss auf <kbd>true</kbd> gesetzt sein.]]></item>
			<item name="wcf.acp.form.minecraftAdd.webchatInterval"><![CDATA[Pause zwischen webchat Nachrichten]]></item>
		</category>
		<category name="wcf.acp.group">
			<item name="wcf.acp.group.option.user.minecraft.dynmap.access"></item>
			<item name="wcf.acp.group.option.user.minecraft.dynmap.accessProtected"></item>
		</category>
		<category name="wcf.endpoint.dynmap">
			<item name="wcf.endpoint.dynmap.spammessage"><![CDATA[Fehler: {if LANGUAGE_USE_INFORMAL_VARIANT}Sie können{else}Du kannst{/if} nur alle %interval% Sekunden eine Nachricht schreiben.]]></item>
			<item name="wcf.endpoint.dynmap.joinmessage"><![CDATA[%playername% hat den Server betreten.]]></item>
			<item name="wcf.endpoint.dynmap.quitmessage"><![CDATA[%playername% hat den Server verlassen.]]></item>
			<item name="wcf.endpoint.dynmap.msg-chatnotallowed"><![CDATA[Es ist {if LANGUAGE_USE_INFORMAL_VARIANT}ihnen{else}dir{/if} nicht erlaubt, Chat-Nachrichten zu senden.]]></item>
		</category>
	</import>
</language>
